Verilog/JK-FlipFlop/11-JK-Flipflop.v
module jkff(input j , input k , input clk , output reg q , output reg qb);
initial q=0;
always @(posedge clk)begin
    if(j)begin
        if(k)begin
            q=~q;
            qb=~qb;
        end
        if(~k)begin
            q=1;
            qb=0;
        end
    end
    if(~j)begin
        if(k)begin
            q=0;
            qb=1;
        end
    end
end
endmodule

Verilog/JK-FlipFlop/11-JK-Flipflop-tb.v
`timescale 1ps/1ps
module jktb();
reg j , k , clk=0;
wire q , qb;

jkff uut(.j(j) , .k(k) , .clk(clk) , .q(q) , .qb(qb));

initial begin
    forever #2 clk = ~clk;
end

initial begin
    $dumpfile("jkf.vcd");
    $dumpvars(0 , jktb);
end

initial begin
$monitor("time = %d , j = %d , k = %d , q = %d , qb = %d" , clk , j , k, q ,qb);
j=0 ; k=0;
#2
j=0 ; k=1;
#2
j=1 ; k=0;
#2
j=1 ; k=0;
#2
j=0 ; k=0;
#2
j=0 ; k=1;
#2
j=1 ; k=0;
#2
j=1 ; k=1;
$finish();
end
endmodule

Verilog/11-JKff.vcd
$date
	Thu Oct  5 21:17:38 2023
$end
$version
	Icarus Verilog
$end
$timescale
	1ps
$end
$scope module jktb $end
$var wire 1 ! qb $end
$var wire 1 " q $end
$var reg 1 # clk $end
$var reg 1 $ j $end
$var reg 1 % k $end
$scope module uut $end
$var wire 1 # clk $end
$var wire 1 $ j $end
$var wire 1 % k $end
$var reg 1 " q $end
$var reg 1 ! qb $end
$upscope $end
$upscope $end
$enddefinitions $end
$comment Show the parameter values. $end
$dumpall
$end
#0
$dumpvars
0%
0$
0#
0"
x!
$end
#2
1!
1%
1#
#4
0%
1$
0#
#6
0!
1"
1#
#8
0$
0#
#10
1!
0"
1%
1#
#12
0%
1$
0#
#14
0!
1"
1%
1#
