Verilog/13-Counter.v
module counter(input reset , input clk , output [2:0]out );
reg [2:0]count;

always @(posedge clk or reset)
begin
    if(reset)
    count <= 3'd0;
    else
    if(count == 3'd6 || count==3'd7)
    count <=3'd0;
    else 
    count <= count + 3'd1;
end
assign out = count;
endmodule

Verilog/13-Counter-tb.v
`timescale 1ps/1ps;
`include "13-Counter.v"
module ctb();
reg reset , clk;
wire [2:0] out;
counter c1(.reset(reset) , .clk(clk) , .out(out));

initial begin 
clk=0;
forever #5 clk=~clk;
end
initial begin
    $dumpfile("out.vcd");
    $dumpvars(0, ctb);
reset=1;
#15;
reset=0;
#200;
$finish;
reset=0;
end
endmodule

Verilog/out.vcd
$date
	Fri Nov  3 10:23:51 2023
$end
$version
	Icarus Verilog
$end
$timescale
	1ps
$end
$scope module ctb $end
$var wire 3 ! out [2:0] $end
$var reg 1 " clk $end
$var reg 1 # reset $end
$scope module c1 $end
$var wire 1 " clk $end
$var wire 3 $ out [2:0] $end
$var wire 1 # reset $end
$var reg 3 % count [2:0] $end
$upscope $end
$upscope $end
$enddefinitions $end
$comment Show the parameter values. $end
$dumpall
$end
#0
$dumpvars
b0 %
b0 $
1#
0"
b0 !
$end
#5
1"
#10
0"
#15
b1 !
b1 $
b1 %
1"
0#
#20
0"
#25
b10 !
b10 $
b10 %
1"
#30
0"
#35
b11 !
b11 $
b11 %
1"
#40
0"
#45
b100 !
b100 $
b100 %
1"
#50
0"
#55
b101 !
b101 $
b101 %
1"
#60
0"
#65
b110 !
b110 $
b110 %
1"
#70
0"
#75
b0 !
b0 $
b0 %
1"
#80
0"
#85
b1 !
b1 $
b1 %
1"
#90
0"
#95
b10 !
b10 $
b10 %
1"
#100
0"
#105
b11 !
b11 $
b11 %
1"
#110
0"
#115
b100 !
b100 $
b100 %
1"
#120
0"
#125
b101 !
b101 $
b101 %
1"
#130
0"
#135
b110 !
b110 $
b110 %
1"
#140
0"
#145
b0 !
b0 $
b0 %
1"
#150
0"
#155
b1 !
b1 $
b1 %
1"
#160
0"
#165
b10 !
b10 $
b10 %
1"
#170
0"
#175
b11 !
b11 $
b11 %
1"
#180
0"
#185
b100 !
b100 $
b100 %
1"
#190
0"
#195
b101 !
b101 $
b101 %
1"
#200
0"
#205
b110 !
b110 $
b110 %
1"
#210
0"
#215
b0 !
b0 $
b0 %
1"
